ddr_mfc/__init__.py
ddr_mfc/base.py
ddr_mfc/version.py
ddr_mfc-0.0.3.dist-info/METADATA
ddr_mfc-0.0.3.dist-info/WHEEL
ddr_mfc-0.0.3.dist-info/top_level.txt
ddr_mfc-0.0.3.dist-info/RECORD
